rc.py
alias.rc-0.0.2.dist-info/METADATA
alias.rc-0.0.2.dist-info/RECORD
alias.rc-0.0.2.dist-info/WHEEL
alias.rc-0.0.2.dist-info/entry_points.txt
alias.rc-0.0.2.dist-info/top_level.txt
