Metadata-Version: 2.1
Name: alias.rc
Version: 0.0.2
Summary: Keep your bash.rc/zsh.rc command lines across all your devices
Home-page: UNKNOWN
Author: Omer M. A.
Author-email: om@env.li
License: Apache2
Platform: UNKNOWN
Requires-Dist: Click
Requires-Dist: usersettings
Requires-Dist: simple-crypt
